{
  "dwg": "BINARY RECEPTION AND PANTRY.dwg",
  "tab": "layers",
  "items": [
    {
      "layer": "CORNER PROFILE STRIP",
      "zone": "RECEPTION & WAITING AREA",
      "remarks": "OPEN length only",
      "length (ft)": 13.3596,
      "width (ft)": 0,
      "perimeter": 0,
      "area (ft2)": 0
    },
    {
      "layer": "FLR- NYLON CARPET",
      "zone": "CAFETERIA",
      "remarks": "CLOSED (rectangle): length/width + perimeter & area",
      "length (ft)": 12.423,
      "width (ft)": 8.6915,
      "perimeter": 42.2289,
      "area (ft2)": 107.974
    },
    {
      "layer": "FLR- NYLON CARPET",
      "zone": "RECEPTION & WAITING AREA",
      "remarks": "CLOSED (rectangle): length/width + perimeter & area",
      "length (ft)": 13.5067,
      "width (ft)": 8.2671,
      "perimeter": 43.5475,
      "area (ft2)": 111.6609
    },
    {
      "layer": "GLASS CLAD",
      "zone": "RECEPTION & WAITING AREA",
      "remarks": "OPEN length only",
      "length (ft)": 8.1941,
      "width (ft)": 0,
      "perimeter": 0,
      "area (ft2)": 0
    },
    {
      "layer": "GRANITE",
      "zone": "CAFETERIA",
      "remarks": "CLOSED (rectangle): length/width + perimeter & area",
      "length (ft)": 6.1167,
      "width (ft)": 1.9685,
      "perimeter": 16.1705,
      "area (ft2)": 12.0408
    },
    {
      "layer": "MODULAR SKIRITING 75MM",
      "zone": "CAFETERIA",
      "remarks": "OPEN length only",
      "length (ft)": 21.1144,
      "width (ft)": 0,
      "perimeter": 0,
      "area (ft2)": 0
    },
    {
      "layer": "PANELING- LAMINATE",
      "zone": "CAFETERIA",
      "remarks": "OPEN length only",
      "length (ft)": 12.3004,
      "width (ft)": 0,
      "perimeter": 0,
      "area (ft2)": 0
    },
    {
      "layer": "PANELING- LAMINATE",
      "zone": "RECEPTION & WAITING AREA",
      "remarks": "OPEN length only",
      "length (ft)": 13.3613,
      "width (ft)": 0,
      "perimeter": 0,
      "area (ft2)": 0
    },
    {
      "layer": "PDF2_hatch",
      "zone": "misc",
      "remarks": "CLOSED (rectangle): length/width + perimeter & area",
      "length (ft)": 0,
      "width (ft)": 0,
      "perimeter": 0.0453,
      "area (ft2)": 0
    },
    {
      "layer": "WALL DADO TILES",
      "zone": "misc",
      "remarks": "OPEN length only",
      "length (ft)": 8.3634,
      "width (ft)": 0,
      "perimeter": 0,
      "area (ft2)": 0
    },
    {
      "layer": "WALLPAPER -READY",
      "zone": "CAFETERIA",
      "remarks": "OPEN length only",
      "length (ft)": 10.4601,
      "width (ft)": 0,
      "perimeter": 0,
      "area (ft2)": 0
    }
  ]
}
